<?xml version="1.0" encoding="UTF-8"?><courses><course acad_year="2014" cat_num="30212" offered="Y">
<term term_pattern_code="2" fall_term="N" spring_term="Y">spring term</term>
<department code="DEAS">
<dept_long_name>Division of Engineering and Applied Sciences</dept_long_name>
<dept_short_name>Engineering and Applied Sciences</dept_short_name>
</department>
<course_group code="BE">Biomedical Engineering</course_group>
<course_number>
<num_int>191</num_int>
</course_number>
<title>Introduction to Biomaterials</title>
<course_type>Lecture</course_type>
<course_level code="O">For Undergraduates and Graduates</course_level>
<credit code="1">Half course</credit>
<enrollment_limit>30</enrollment_limit>
<meeting_text>Tu., Th., 11:30-1</meeting_text>
<faculty_text>Jennifer Lewis</faculty_text>
<description>A biomaterial is any form of matter that is produced by or interacts with biological systems. One of the pillars of biomedical engineering is to use naturally derived and synthetic biomaterials to treat, augment, or replace human tissues. This course examines the structure, properties and processing of biomaterials.</description>
<prerequisites>Physical sciences 1, Math 1b.</prerequisites>
<notes/>
<instructor_approval_required>Y</instructor_approval_required>
<faculty_list>
<faculty term="2" role="H" id="F743bb8e65fa07a2fbcaeed650126346d">
<name>
<prefix/>
<first>Jennifer</first>
<middle/>
<last>Lewis</last>
<suffix/>
</name>
</faculty>
</faculty_list>
<schedule>
<meeting term="2" optional="N" type="Lecture" day="2" begin_time="1130" end_time="1300"/>
<meeting term="2" optional="N" type="Lecture" day="4" begin_time="1130" end_time="1300"/>
</schedule>
<meeting_locations/>
<requirements/>
</course></courses>