<?xml version="1.0" encoding="UTF-8"?><courses><course acad_year="2014" cat_num="7342" offered="Y">
<term term_pattern_code="4" fall_term="Y" spring_term="Y">full year</term>
<department code="ECON">
<dept_long_name>Department of Economics</dept_long_name>
<dept_short_name>Economics</dept_short_name>
</department>
<course_group code="ECON">Economics</course_group>
<course_number>
<num_int>990</num_int>
</course_number>
<title>Tutorial - Senior Year</title>
<course_type>Tutorial</course_type>
<course_level code="P">Primarily for Undergraduates</course_level>
<credit code="2">Full course</credit>
<meeting_text>Hours to be arranged</meeting_text>
<faculty_text>Jane Leber Herr and members of the Department</faculty_text>
<description>For students writing a senior thesis out of sequence.</description>
<prerequisites/>
<notes>Students who are writing a senior thesis out of sequence (i.e., beginning in the spring) must enroll in Economics 990 in the spring and complete the course in the fall. Students must write a 25-page paper at the end of the first term of Economics 990. Students currently enrolled in Economics 985 may not enroll in Economics 990.</notes>
<instructor_approval_required>Y</instructor_approval_required>
<faculty_list>
<faculty term="1" role="H" id="F807212da7d87a599335786ed90be70d5">
<name>
<prefix/>
<first>Jeffrey</first>
<middle/>
<last>Miron</last>
<suffix/>
</name>
</faculty>
<faculty term="2" role="H" id="F807212da7d87a599335786ed90be70d5">
<name>
<prefix/>
<first>Jeffrey</first>
<middle/>
<last>Miron</last>
<suffix/>
</name>
</faculty>
</faculty_list>
<schedule/>
<meeting_locations/>
<requirements/>
</course></courses>